kulc/__init__.py
kulc/__version__.py
kulc/attention.py
kulc/image.py
kulc/layer_normalization.py
kulc-0.0.9.dist-info/METADATA
kulc-0.0.9.dist-info/RECORD
kulc-0.0.9.dist-info/WHEEL
kulc-0.0.9.dist-info/top_level.txt
