Metadata-Version: 2.1
Name: kulc
Version: 0.0.9
Summary: Keras Utility & Layer Collection.
Home-page: https://github.com/FlashTek/keras-layer-collection
Author: Roland Zimmermann
Author-email: rzrolandzimmermann@gmail.com
License: MIT
Platform: UNKNOWN
Classifier: License :: OSI Approved :: MIT License
Classifier: Programming Language :: Python
Classifier: Programming Language :: Python :: 3
Classifier: Programming Language :: Python :: 3.6
Classifier: Programming Language :: Python :: Implementation :: CPython
Classifier: Programming Language :: Python :: Implementation :: PyPy
Requires-Python: >=3.6.0
